app/__init__.py
app/hello.py
tests/__init__.py
tests/test_hello_world.py
devops_challenge_vchslav-0.1.1.dist-info/METADATA
devops_challenge_vchslav-0.1.1.dist-info/WHEEL
devops_challenge_vchslav-0.1.1.dist-info/top_level.txt
devops_challenge_vchslav-0.1.1.dist-info/RECORD
