Metadata-Version: 2.1
Name: devops-challenge-vchslav
Version: 0.1.1
Summary: Flask app
Home-page: https://github.com/pypa/devops-challenge-vchslav-v011
Author: Slava Bikov
Author-email: slava.bikov@gmail.com
License: UNKNOWN
Platform: UNKNOWN
Classifier: Programming Language :: Python :: 3
Classifier: License :: OSI Approved :: MIT License
Classifier: Operating System :: OS Independent
Requires-Python: >=2.7
